valohai_cli/__init__.py
valohai_cli/adhoc.py
valohai_cli/api.py
valohai_cli/cli.py
valohai_cli/consts.py
valohai_cli/ctx.py
valohai_cli/exceptions.py
valohai_cli/git.py
valohai_cli/help_texts.py
valohai_cli/log_manager.py
valohai_cli/messages.py
valohai_cli/override.py
valohai_cli/packager.py
valohai_cli/plugin_cli.py
valohai_cli/py.typed
valohai_cli/range.py
valohai_cli/table.py
valohai_cli/tui.py
valohai_cli/yaml_wizard.py
valohai_cli/commands/__init__.py
valohai_cli/commands/environments.py
valohai_cli/commands/init.py
valohai_cli/commands/lint.py
valohai_cli/commands/login.py
valohai_cli/commands/logout.py
valohai_cli/commands/parcel.py
valohai_cli/commands/update_check.py
valohai_cli/commands/alias/__init__.py
valohai_cli/commands/alias/list.py
valohai_cli/commands/data/__init__.py
valohai_cli/commands/data/list.py
valohai_cli/commands/deployment/__init__.py
valohai_cli/commands/deployment/create_version/__init__.py
valohai_cli/commands/deployment/create_version/create_version.py
valohai_cli/commands/deployment/create_version/dynamic_creation_command.py
valohai_cli/commands/execution/__init__.py
valohai_cli/commands/execution/delete.py
valohai_cli/commands/execution/info.py
valohai_cli/commands/execution/list.py
valohai_cli/commands/execution/logs.py
valohai_cli/commands/execution/open.py
valohai_cli/commands/execution/outputs.py
valohai_cli/commands/execution/ssh.py
valohai_cli/commands/execution/stop.py
valohai_cli/commands/execution/summarize.py
valohai_cli/commands/execution/watch.py
valohai_cli/commands/execution/run/__init__.py
valohai_cli/commands/execution/run/dynamic_run_command.py
valohai_cli/commands/execution/run/excs.py
valohai_cli/commands/execution/run/frontend_command.py
valohai_cli/commands/execution/run/utils.py
valohai_cli/commands/notebook/__init__.py
valohai_cli/commands/notebook/run/__init__.py
valohai_cli/commands/notebook/run/run.py
valohai_cli/commands/pipeline/__init__.py
valohai_cli/commands/pipeline/convert_to_api.py
valohai_cli-0.35.0.dist-info/METADATA
valohai_cli-0.35.0.dist-info/WHEEL
valohai_cli-0.35.0.dist-info/entry_points.txt
valohai_cli-0.35.0.dist-info/licenses/LICENSE
valohai_cli-0.35.0.dist-info/RECORD
