Metadata-Version: 2.4
Name: valohai-cli
Version: 0.35.0
Summary: Command line client for Valohai
Project-URL: Homepage, https://github.com/valohai/valohai-cli
Author-email: Valohai <hait@valohai.com>
License-Expression: MIT
License-File: LICENSE
Requires-Python: >=3.9
Requires-Dist: click<8.2,>=8.0
Requires-Dist: gitignorant>=0.4.0
Requires-Dist: requests-toolbelt>=0.7.1
Requires-Dist: requests>=2.0.0
Requires-Dist: valohai-utils>=0.5.0
Requires-Dist: valohai-yaml>=0.51.0
Provides-Extra: test
Requires-Dist: pytest-cov>=4.0; extra == 'test'
Requires-Dist: pytest>=7.0; extra == 'test'
Requires-Dist: requests-mock~=1.10; extra == 'test'
